Metadata-Version: 2.4
Name: oracle.oci-object-storage-mcp-server
Version: 1.1.0
Summary: OCI Object Storage Service MCP server
Author-email: Oracle MCP <237432095+oracle-mcp@users.noreply.github.com>
License-File: LICENSE.txt
Classifier: License :: OSI Approved :: Universal Permissive License (UPL)
Classifier: Operating System :: OS Independent
Classifier: Programming Language :: Python
Classifier: Programming Language :: Python :: 3.13
Requires-Python: >=3.13
Requires-Dist: fastmcp==2.13.0
Requires-Dist: oci==2.160.0
